python_fm_dapi_weaver/__init__.py
python_fm_dapi_weaver/main.py
python_fm_dapi_weaver/controllers/__init__.py
python_fm_dapi_weaver/controllers/auth.py
python_fm_dapi_weaver/controllers/index.py
python_fm_dapi_weaver/controllers/records.py
python_fm_dapi_weaver/routes/__init__.py
python_fm_dapi_weaver/routes/index.py
python_fm_dapi_weaver/utils/__init__.py
python_fm_dapi_weaver/utils/helpers.py
python_fm_dapi_weaver-1.2.1.dist-info/licenses/LICENSE
python_fm_dapi_weaver-1.2.1.dist-info/METADATA
python_fm_dapi_weaver-1.2.1.dist-info/WHEEL
python_fm_dapi_weaver-1.2.1.dist-info/top_level.txt
python_fm_dapi_weaver-1.2.1.dist-info/RECORD
